#### 1.自己写一个简单的hello.java,里面需要设计基本类型，四则运算，if和for,然后自己分析一下对应的字节码

Java代码

```java
public class Hello {
    public static void main(String[] args) {
        int a =1;
        double b = 0.5;
        double c = a+b;
        if (a+b == c){
            System.out.println("true");
        }
        for (int i = 0;i<10;i++){
            a++;
        }
    }
}
```

反编译后的字节码

```
 descriptor: ([Ljava/lang/String;)V
    flags: ACC_PUBLIC, ACC_STATIC
    Code:
      stack=4, locals=7, args_size=1
         0: iconst_1    //int类型1入栈，栈顶值=1
         1: istore_1    //将栈顶的int数值存入第二个本地变量
         2: ldc2_w   #2 //将long或者double类型常量从常量池推送至栈顶
         5: dstore_2  //将栈顶double型数值存入第三个本地变量
         6: iload_1    //将第二个int型本地变量推送至栈顶
         7: i2d        //将栈顶int型数值强制转换为double型数值并将结果压入栈顶
         8: dload_2     //将第三个double型本地变量推送至栈顶
         9: dadd        //将栈顶两double型数值相加并将结果压入栈顶
        10: dstore       4//将栈顶double型数值存入指定本地变量
        12: iload_1      //将第二个int型本地变量推送至栈顶
        13: i2d          //将栈顶int型数值强制转换为double型数值并将结果压入栈顶
        14: dload_2      //将第三个double型本地变量推送至栈顶
        15: dadd         //将栈顶两double型数值相加并将结果压入栈顶
        16: dload         4//将指定的double型本地变量推送至栈顶
        18: dcmpl        //比较栈顶两double型数值大小, 并将结果(1, 0或-1)压入栈顶; 当其中一个数值为NaN时, 将-1压入栈顶
        19: ifne          30  // 当栈顶int型数值不等于0时跳转
        22: getstatic     #4  //获取指定类的静态域, 并将其压入栈顶                // Field java/lang/System.out:Ljava/io/PrintStream;
        25: ldc           #5  //将int,float或String型常量值从常量池中推送至栈顶                // String true
        27: invokevirtual #6   //调用实例方法               // Method java/io/PrintStream.println:(Ljava/lang/String;)V
        30: iconst_0     //将int型0推送至栈顶
        31: istore        6  //将栈顶int型数值存入指定本地变量
        33: iload         6   //将指定的int型本地变量推送至栈顶
        35: bipush        10   //将单字节的常量值(-128~127)推送至栈顶
        37: if_icmpge     49   比较栈顶两int型数值大小, 当结果大于等于0时跳转
        40: iinc          1, 1   //将指定int型变量增加指定值(如i++, i--, i+=2等)
        43: iinc          6, 1  //将指定int型变量增加指定值(如i++, i--, i+=2等)
        46: goto          33  无条件跳转
        49: return
      LineNumberTable:
        line 7: 0
        line 8: 2
        line 9: 6
        line 10: 12
        line 11: 22
        line 13: 30
        line 14: 40
        line 13: 43
        line 16: 49
      StackMapTable: number_of_entries = 3
        frame_type = 254 /* append */
          offset_delta = 30
          locals = [ int, double, double ]
        frame_type = 252 /* append */
          offset_delta = 2
          locals = [ int ]
        frame_type = 250 /* chop */
          offset_delta = 15
}
SourceFile: "Hello.java"
```

本次代码运算，第一部分包含了基本逻辑就是int值入栈(iconst)，int值出栈(istore)，double值入栈(ldc2_w)，double值出栈(dstore),完成变量a、b的声明和初始化，a变量的类型转换，然后将a,b的值压入栈中，使用dadd等操作运算符进行计算。

```
18: dcmpl        //比较栈顶两double型数值大小, 并将结果(1, 0或-1)压入栈顶; 当其中一个数值为NaN时, 将-1压入栈顶
19: ifne          30  // 当栈顶int型数值不等于0时跳转
22: getstatic     #4  //获取指定类的静态域, 并将其压入栈顶                // Field java/lang/System.out:Ljava/io/PrintStream;
 25: ldc           #5  //将int,float或String型常量值从常量池中推送至栈顶                // String true
27: invokevirtual #6   //调用实例方法               // Method java/io/PrintStream.println:(Ljava/lang/String;)V
```



第二部分是if判断,将栈顶的两个数值进行比较，讲比较结果压入栈(dcmpl),在进行if判断，判断 当前栈顶的值是否等0(ifne)。

```
30: iconst_0     //将int型0推送至栈顶
31: istore        6  //将栈顶int型数值存入指定本地变量
33: iload         6   //将指定的int型本地变量推送至栈顶
35: bipush        10   //将单字节的常量值(-128~127)推送至栈顶
37: if_icmpge     49   比较栈顶两int型数值大小, 当结果大于等于0时跳转
40: iinc          1, 1   //将指定int型变量增加指定值(如i++, i--, i+=2等)
43: iinc          6, 1  //将指定int型变量增加指定值(如i++, i--, i+=2等)
46: goto          33  无条件跳转
49: return
```



第三部分是进行for循环30-33是生成初始化int类型i，并进行赋值压入栈，37行进行进行比较大小，如果大于，则跳转到49行，否者执行40行。再讲int类型值进行自增，跳转到33行，从新进行判断。

